Graphite/__init__.py
graphiteinter-0.5.3.dist-info/METADATA
graphiteinter-0.5.3.dist-info/WHEEL
graphiteinter-0.5.3.dist-info/top_level.txt
graphiteinter-0.5.3.dist-info/RECORD
